pytorch_metric_learning/__init__.py
pytorch_metric_learning/datasets/__init__.py
pytorch_metric_learning/datasets/base_dataset.py
pytorch_metric_learning/datasets/cars196.py
pytorch_metric_learning/datasets/cub.py
pytorch_metric_learning/datasets/inaturalist2018.py
pytorch_metric_learning/datasets/sop.py
pytorch_metric_learning/distances/__init__.py
pytorch_metric_learning/distances/base_distance.py
pytorch_metric_learning/distances/batched_distance.py
pytorch_metric_learning/distances/cosine_similarity.py
pytorch_metric_learning/distances/dot_product_similarity.py
pytorch_metric_learning/distances/lp_distance.py
pytorch_metric_learning/distances/snr_distance.py
pytorch_metric_learning/losses/__init__.py
pytorch_metric_learning/losses/angular_loss.py
pytorch_metric_learning/losses/arcface_loss.py
pytorch_metric_learning/losses/base_loss_wrapper.py
pytorch_metric_learning/losses/base_metric_loss_function.py
pytorch_metric_learning/losses/circle_loss.py
pytorch_metric_learning/losses/contrastive_loss.py
pytorch_metric_learning/losses/cosface_loss.py
pytorch_metric_learning/losses/cross_batch_memory.py
pytorch_metric_learning/losses/dynamic_soft_margin_loss.py
pytorch_metric_learning/losses/fast_ap_loss.py
pytorch_metric_learning/losses/generic_pair_loss.py
pytorch_metric_learning/losses/histogram_loss.py
pytorch_metric_learning/losses/instance_loss.py
pytorch_metric_learning/losses/intra_pair_variance_loss.py
pytorch_metric_learning/losses/large_margin_softmax_loss.py
pytorch_metric_learning/losses/lifted_structure_loss.py
pytorch_metric_learning/losses/manifold_loss.py
pytorch_metric_learning/losses/margin_loss.py
pytorch_metric_learning/losses/mixins.py
pytorch_metric_learning/losses/multi_similarity_loss.py
pytorch_metric_learning/losses/multiple_losses.py
pytorch_metric_learning/losses/n_pairs_loss.py
pytorch_metric_learning/losses/nca_loss.py
pytorch_metric_learning/losses/normalized_softmax_loss.py
pytorch_metric_learning/losses/ntxent_loss.py
pytorch_metric_learning-2.9.0.dist-info/LICENSE
pytorch_metric_learning-2.9.0.dist-info/METADATA
pytorch_metric_learning-2.9.0.dist-info/WHEEL
pytorch_metric_learning-2.9.0.dist-info/top_level.txt
pytorch_metric_learning-2.9.0.dist-info/RECORD
