Metadata-Version: 2.1
Name: pytorch-metric-learning
Version: 2.9.0
Summary: The easiest way to use deep metric learning in your application. Modular, flexible, and extensible. Written in PyTorch.
Home-page: https://github.com/KevinMusgrave/pytorch-metric-learning
Author: Kevin Musgrave
License: UNKNOWN
Platform: UNKNOWN
Classifier: Programming Language :: Python :: 3
Classifier: License :: OSI Approved :: MIT License
Classifier: Operating System :: OS Independent
Requires-Python: >=3.0
Provides-Extra: dev
Provides-Extra: docs
Provides-Extra: with-hooks
Provides-Extra: with-hooks-cpu
